Metadata-Version: 2.1
Name: jderobot-interfaces-python
Version: 0.1.6
Summary: Package that includes all the JdeRobot python interfaces
Home-page: https://github.com/jderobot/jderobot.git
Author: Francisco Perez
Author-email: f.perez475@gmail.com
License: UNKNOWN
Project-URL: Bug Reports, https://answers.jderobot.org
Project-URL: Forum, https://developers.jderobot.org
Project-URL: Web, https://jderobot.org
Project-URL: Source, https://github.com/jderobot/jderobot.git
Keywords: JdeRobot interfaces python
Platform: UNKNOWN
Classifier: Development Status :: 3 - Alpha
Classifier: Intended Audience :: Education
Classifier: Intended Audience :: Developers
Classifier: Topic :: Software Development :: Build Tools
Classifier: Topic :: Education
Classifier: License :: OSI Approved :: GNU General Public License v3 (GPLv3)
Classifier: Programming Language :: Python :: 2.7
Classifier: Programming Language :: Python :: 3.5
